LICENCE.txt
MANIFEST.in
README.txt
setup.py
django_moj_template.egg-info/PKG-INFO
django_moj_template.egg-info/SOURCES.txt
django_moj_template.egg-info/dependency_links.txt
django_moj_template.egg-info/requires.txt
django_moj_template.egg-info/top_level.txt
moj_template/__init__.py
moj_template/static/images/apple-touch-icon-120x120.png
moj_template/static/images/apple-touch-icon-152x152.png
moj_template/static/images/apple-touch-icon-60x60.png
moj_template/static/images/apple-touch-icon-76x76.png
moj_template/static/images/favicon.ico
moj_template/static/images/gov.uk_logotype_crown.png
moj_template/static/images/gov.uk_logotype_crown_invert.png
moj_template/static/images/gov.uk_logotype_crown_invert_trans.png
moj_template/static/images/opengraph-image.png
moj_template/static/javascripts/govuk-template.js
moj_template/static/javascripts/ie.js
moj_template/static/javascripts/moj.js
moj_template/static/javascripts/modules/moj.tabs.js
moj_template/static/javascripts/vendor/goog/webfont-debug.js
moj_template/static/javascripts/vendor/jquery/jquery-1.11.0.min.js
moj_template/static/stylesheets/fonts-ie8.css
moj_template/static/stylesheets/fonts.css
moj_template/static/stylesheets/govuk-template-ie6.css
moj_template/static/stylesheets/govuk-template-ie7.css
moj_template/static/stylesheets/govuk-template-ie8.css
moj_template/static/stylesheets/govuk-template-print.css
moj_template/static/stylesheets/govuk-template.css
moj_template/static/stylesheets/moj-template-ie6.css
moj_template/static/stylesheets/moj-template-ie7.css
moj_template/static/stylesheets/moj-template-ie8.css
moj_template/static/stylesheets/moj-template.css
moj_template/static/stylesheets/external-links/external-link-24x24.png
moj_template/static/stylesheets/external-links/external-link-black-12x12.png
moj_template/static/stylesheets/external-links/external-link-black-24x24.png
moj_template/static/stylesheets/external-links/external-link.png
moj_template/static/stylesheets/fonts/NTA-Bold-20130221.eot
moj_template/static/stylesheets/fonts/NTA-Bold-20130221.woff
moj_template/static/stylesheets/fonts/NTA-Light-20130221.eot
moj_template/static/stylesheets/fonts/NTA-Light-20130221.woff
