Metadata-Version: 1.1
Name: django-moj-template
Version: 0.23.1
Summary: MOJ Template
Home-page: https://github.com/ministryofjustice/moj_template
Author: Dom Smith
Author-email: dom.smith@digital.justice.gov.uk
License: MIT
Keywords: python,django,ministryofjustice,govuk
Platform: any
Classifier: Programming Language :: Python
Classifier: License :: OSI Approved :: MIT License
Classifier: Operating System :: OS Independent
Classifier: Development Status :: 3 - Alpha
Classifier: Environment :: Web Environment
Classifier: Intended Audience :: Developers
Classifier: Topic :: Software Development :: Libraries :: Python Modules
